NikClip/__init__.py
NikClip-2.1.1.dist-info/LICENSE
NikClip-2.1.1.dist-info/METADATA
NikClip-2.1.1.dist-info/WHEEL
NikClip-2.1.1.dist-info/top_level.txt
NikClip-2.1.1.dist-info/RECORD
