Metadata-Version: 2.1
Name: NikClip
Version: 2.1.1
Summary: A full fledged media-player and media-downloader
Home-page: https://github.com/Nikhilodeon1/NikClip
Author: Nikhil Tamvada (Nikhilodeon1)
Author-email: nikhiltamvada@gmail.com
Classifier: Programming Language :: Python :: 3
Classifier: License :: OSI Approved :: MIT License
Classifier: Operating System :: OS Independent
Requires-Python: >=3.8
License-File: LICENSE
